halea/__init__.py
halea/_base.py
halea/_version.py
halea/exceptions.py
halea/jax.py
halea/numpy.py
halea/torch.py
halea/backends/__init__.py
halea/backends/_chaoskey.py
halea/backends/_truerng.py
halea-0.0.1.dist-info/licenses/LICENSE
halea-0.0.1.dist-info/METADATA
halea-0.0.1.dist-info/WHEEL
halea-0.0.1.dist-info/top_level.txt
halea-0.0.1.dist-info/zip-safe
halea-0.0.1.dist-info/RECORD
