Metadata-Version: 2.4
Name: halea
Version: 0.0.1
Summary: Unified access to (some) hardware RNGs for machine learning & scientific computing
Author-email: Emanuele Ballarin <emanuele@ballarin.cc>
License: MIT
Project-URL: Homepage, https://github.com/emaballarin/halea
Keywords: chaoskey,entropy,hardware-rng,jax,numpy,pytorch,random,truerng
Classifier: Development Status :: 3 - Alpha
Classifier: Topic :: Scientific/Engineering :: Mathematics
Classifier: Topic :: System :: Hardware :: Universal Serial Bus (USB) :: Miscellaneous
Classifier: Intended Audience :: Science/Research
Classifier: Environment :: Console
Classifier: Programming Language :: Python :: 3
Classifier: License :: OSI Approved :: MIT License
Requires-Python: >=3.11
License-File: LICENSE
Requires-Dist: numpy>=1.24
Provides-Extra: chaoskey
Requires-Dist: pyusb>=1.2; extra == "chaoskey"
Provides-Extra: jax
Requires-Dist: jax>=0.4; extra == "jax"
Requires-Dist: jaxlib>=0.4; extra == "jax"
Provides-Extra: torch
Requires-Dist: torch>=2.0; extra == "torch"
Provides-Extra: truerng
Requires-Dist: pyserial>=3.5; extra == "truerng"
Provides-Extra: test
Requires-Dist: pytest>=8.3; extra == "test"
Requires-Dist: pytest-cov>=7; extra == "test"
Requires-Dist: pytest-mock>=3.15; extra == "test"
Provides-Extra: all
Requires-Dist: pyserial>=3.5; extra == "all"
Requires-Dist: pyusb>=1.2; extra == "all"
Requires-Dist: torch>=2.0; extra == "all"
Requires-Dist: jax>=0.4; extra == "all"
Requires-Dist: jaxlib>=0.4; extra == "all"
Requires-Dist: pytest>=8.3; extra == "all"
Requires-Dist: pytest-cov>=7; extra == "all"
Requires-Dist: pytest-mock>=3.15; extra == "all"
Dynamic: license-file
